[
    {
        "fish": "Акула катран",
        "activity": {
            "Янв": "нет клева",
            "Фев": "нет клева",
            "Мар": "слабый клев",
            "Апр": "средний клев",
            "Май": "средний клев",
            "Июн": "хороший клев",
            "Июл": "средний клев",
            "Авг": "средний клев",
            "Сен": "слабый клев",
            "Окт": "нет клева",
            "Ноя": "нет клева",
            "Дек": "нет клева"
        }
    },
    {
        "fish": "Акула-домовой",
        "activity": {
            "Янв": "нет клева",
            "Фев": "нет клева",
            "Мар": "слабый клев",
            "Апр": "слабый клев",
            "Май": "средний клев",
            "Июн": "средний клев",
            "Июл": "хороший клев",
            "Авг": "хороший клев",
            "Сен": "средний клев",
            "Окт": "слабый клев",
            "Ноя": "нет клева",
            "Дек": "нет клева"
        }
    },
    {
        "fish": "Аллигаторовая щука",
        "activity": {
            "Янв": "нет клева",
            "Фев": "слабый клев",
            "Мар": "слабый клев",
            "Апр": "средний клев",
            "Май": "средний клев",
            "Июн": "хороший клев",
            "Июл": "хороший клев",
            "Авг": "средний клев",
            "Сен": "слабый клев",
            "Окт": "нет клева",
            "Ноя": "нет клева",
            "Дек": "нет клева"
        }
    },
    {
        "fish": "Альбула",
        "activity": {
            "Янв": "слабый клев",
            "Фев": "слабый клев",
            "Мар": "средний клев",
            "Апр": "средний клев",
            "Май": "хороший клев",
            "Июн": "хороший клев",
            "Июл": "средний клев",
            "Авг": "средний клев",
            "Сен": "слабый клев",
            "Окт": "слабый клев",
            "Ноя": "нет клева",
            "Дек": "нет клева"
        }
    },
    {
        "fish": "Арапайма",
        "activity": {
            "Янв": "нет клева",
            "Фев": "слабый клев",
            "Мар": "средний клев",
            "Апр": "средний клев",
            "Май": "хороший клев",
            "Июн": "средний клев",
            "Июл": "средний клев",
            "Авг": "слабый клев",
            "Сен": "слабый клев",
            "Окт": "нет клева",
            "Ноя": "нет клева",
            "Дек": "нет клева"
        }
    },
    {
        "fish": "Ауха",
        "activity": {
            "Янв": "нет клева",
            "Фев": "нет клева",
            "Мар": "слабый клев",
            "Апр": "средний клев",
            "Май": "хороший клев",
            "Июн": "хороший клев",
            "Июл": "средний клев",
            "Авг": "нет клева",
            "Сен": "слабый клев",
            "Окт": "нет клева",
            "Ноя": "средний клев",
            "Дек": "нет клева"
        }
    },
    {
        "fish": "Барабуля",
        "activity": {
            "Янв": "слабый клев",
            "Фев": "нет клева",
            "Мар": "слабый клев",
            "Апр": "средний клев",
            "Май": "хороший клев",
            "Июн": "средний клев",
            "Июл": "средний клев",
            "Авг": "нет клева",
            "Сен": "слабый клев",
            "Окт": "слабый клев",
            "Ноя": "нет клева",
            "Дек": "нет клева"
        }
    }
]
